{
  "category": "LUGAR",
  "items": [
    {
      "name": "Paris",
      "clues": [
        "Sou a cidade da luz.", "Minha Torre é um ícone mundial.", "Sou conhecida por minha arte e cultura.", "O Rio Sena me atravessa.", "Minha gastronomia é renomada.",
        "Sou o lar de museus famosos como o Louvre.", "Minha história é rica e cheia de revoluções.", "Sou um destino romântico.", "Minha arquitetura é deslumbrante.", "O Champs-Élysées é meu cartão-postal.",
        "Sou famosa por minha moda e estilo.", "O Arco do Triunfo me representa.", "Sou um centro de inovação e tecnologia.", "Minha diversidade cultural é marcante.",
        "Sou palco de eventos internacionais.", "Minha história é marcada por guerras e paz.", "Sou um destino turístico popular.", "Sou um símbolo de liberdade e igualdade.", "Minha beleza é eterna.", "Sou inspiração para poetas e artistas."
      ]
    },
    {
      "name": "Tóquio",
      "clues": [
        "Sou a capital do Japão.", "Minha modernidade contrasta com tradições antigas.", "Sou conhecida por minha tecnologia avançada.", "O Monte Fuji me observa ao longe.", "Minha gastronomia é famosa mundialmente.",
        "Sou um centro de cultura pop e anime.", "Minha arquitetura é futurista e tradicional.", "Sou um destino vibrante e dinâmico.", "Minha vida noturna é eletrizante.", "Sou palco de festivais e eventos culturais.",
        "Minha história é rica e complexa.", "Sou um centro financeiro global.", "Minha população é uma das maiores do mundo.", "Sou conhecida por minha eficiência no transporte público.", "Minha arte e design são inovadores.",
        "Sou um destino turístico popular.", "Minha cultura é uma mistura de antigo e moderno.", "Sou um símbolo de resiliência e inovação.", "Minha influência na moda é significativa.", "Sou um lugar onde tradição e futuro se encontram."
      ]
    },
    {
      "name": "Nova York",
      "clues": [
        "Sou a cidade que nunca dorme.", "Minha Estátua da Liberdade é um ícone de liberdade.", "Sou conhecida por minha diversidade cultural.", "O Central Park é meu pulmão verde.", "Minha skyline é deslumbrante.",
        "Sou um centro financeiro global.", "Minha Broadway é famosa por seus espetáculos.", "Sou um destino turístico popular.", "Minha história é marcada por imigração e inovação.", "Sou um centro de arte e cultura.",
        "Minha Times Square é um símbolo de energia.", "Sou palco de eventos internacionais.", "Minha gastronomia é variada e deliciosa.", "Sou um centro de moda e estilo.", "Minha vida noturna é vibrante.",
        "Sou um lugar onde sonhos se tornam realidade.", "Minha influência na música é significativa.", "Sou um símbolo de liberdade e oportunidades.", "Minha história é rica e complexa.", "Sou um destino icônico e inesquecível."
      ]
    },
    {
      "name": "Machu Picchu",
      "clues": [
        "Sou uma cidade perdida nas montanhas.", "Minha história é envolta em mistério.", "Sou um Patrimônio Mundial da UNESCO.", "Minha arquitetura é impressionante e antiga.",
        "Sou um destino sagrado para os incas.", "Minha localização é de tirar o fôlego.", "Sou cercada por lendas e tradições.", "Minha descoberta foi um marco arqueológico.", "Sou um símbolo da civilização inca.",
        "Minha beleza natural é deslumbrante.", "Sou um destino turístico popular.", "Minha história é rica e fascinante.", "Sou um lugar de espiritualidade e reflexão.", "Minha preservação é crucial para a cultura peruana.",
        "Sou um testemunho da engenharia antiga.", "Minha trilha é desafiadora.", "Sou um lugar onde passado e presente se encontram.", "Sou um destino de aventura e descoberta.", "Minha beleza é única e inspiradora.", "Sou um símbolo de resistência e resiliência."
      ]
    },
    {
      "name": "Rio Amazonas",
      "clues": [
        "Sou o maior rio em volume de água do mundo.", "Minha bacia atravessa vários países da América do Sul.", "Minha biodiversidade é impressionante.", "Sou fundamental para o ecossistema amazônico.", "Minha extensão ultrapassa 6 mil quilômetros.",
        "Sou lar de comunidades ribeirinhas.", "Minha nascente está nos Andes.", "Sou tema de estudos científicos e ambientais.", "Minha fauna inclui botos e peixes exóticos.", "Sou símbolo de riqueza natural e desafios ambientais.",
        "Minha navegação é essencial para o transporte regional.", "Sou fonte de inspiração para lendas e mitos.", "Minha importância econômica é vital para a região.", "Sou cenário de expedições históricas.", "Minha água abriga espécies únicas.",
        "Sou tema de debates sobre preservação ambiental.", "Minha paisagem muda entre florestas e cidades.", "Sou símbolo de conexão entre povos.", "Minha força é admirada por exploradores.", "Sou testemunha de mudanças climáticas."
      ]
    },

    {
      "name": "Copacabana",
      "clues": [
        "Sou um dos bairros mais famosos do Rio de Janeiro.", "Minha praia é cartão-postal internacional.", "Meu calçadão tem ondas desenhadas em pedras portuguesas.", "Sou palco de grandes eventos e shows.", "Minha orla é movimentada dia e noite.",
        "Sou destino de turistas do mundo inteiro.", "Sou símbolo da cultura carioca.", "Minha história envolve festas e celebrações.", "Sou cenário de Réveillon com fogos de artifício.", "Sou inspiração para músicas e filmes.",
        "Minha areia é palco de esportes e lazer.", "Sou cercada por hotéis históricos.", "Minha fama ultrapassa fronteiras.", "Sou tema de obras literárias.", "Minha energia contagia visitantes.",
        "Sou símbolo de hospitalidade carioca.", "Minha paisagem é admirada por artistas.", "Sou referência em turismo internacional.", "Minha história é marcada por transformações urbanas.", "Sou cenário de encontros inesquecíveis."
      ]
    },

    {
      "name": "Shopping Iguatemi",
      "clues": [
        "Sou um dos primeiros shoppings do Brasil.", "Minha arquitetura é referência em centros comerciais.", "Sou conhecido por lojas de luxo e gastronomia.", "Minha localização é estratégica em grandes cidades.", "Sou destino de compras e lazer.",
        "Minha história envolve inovação no varejo.", "Sou palco de eventos culturais e exposições.", "Minha marca é reconhecida nacionalmente.", "Sou símbolo de consumo e entretenimento.", "Minha estrutura oferece conforto e segurança.",
        "Sou referência em experiências de compra.", "Minha evolução acompanha tendências do mercado.", "Sou destino de famílias e jovens.", "Minha presença é marcante em datas comemorativas.", "Sou tema de campanhas publicitárias inovadoras.",
        "Minha história é ligada ao desenvolvimento urbano.", "Sou símbolo de modernidade e tradição.", "Minha estrutura recebe visitantes de todo o país.", "Sou inspiração para outros centros comerciais.", "Minha marca valoriza o atendimento ao cliente."
      ]
    },

    {
      "name": "São Paulo",
      "clues": [
        "Sou a maior cidade do Brasil em população.", "Minha economia é uma das mais fortes da América Latina.", "Sou conhecida por minha diversidade cultural.", "Minha Avenida Paulista é símbolo de modernidade.", "Sou polo de negócios, arte e gastronomia.",
        "Minha vida noturna é agitada.", "Sou palco de grandes eventos internacionais.", "Minha história é marcada por imigração.", "Sou referência em inovação e tecnologia.", "Minha influência é nacional e global.",
        "Sou lar de museus e teatros renomados.", "Minha gastronomia é reconhecida mundialmente.", "Sou referência em moda e design.", "Minha mobilidade urbana é desafiadora.", "Sou símbolo de trabalho e oportunidades.",
        "Minha arquitetura mistura estilos antigos e modernos.", "Sou destino de estudantes e profissionais.", "Minha cultura é celebrada em festivais diversos.", "Sou inspiração para artistas e escritores.", "Minha história é marcada por crescimento acelerado."
      ]
    },

    {
      "name": "Bahia",
      "clues": [
        "Sou um estado brasileiro com forte influência africana.", "Minha capital é Salvador.", "Sou conhecido por festas populares e culinária marcante.", "Minha costa é repleta de praias paradisíacas.", "Sou berço do axé e do samba de roda.",
        "Minha história envolve colonização e resistência.", "Sou destino turístico internacional.", "Minha cultura é celebrada em todo o Brasil.", "Sou símbolo de alegria e hospitalidade.", "Minha religiosidade é marcada pelo sincretismo.",
        "Sou palco de festas como o Carnaval e o São João.", "Minha culinária inclui acarajé e moqueca.", "Sou referência em literatura e arte popular.", "Minha paisagem inclui chapadas e manguezais.", "Sou símbolo de fé e tradição.",
        "Minha música influencia o Brasil inteiro.", "Sou destino de turistas em busca de cultura e lazer.", "Minha história é marcada por resistência cultural.", "Sou inspiração para poetas e músicos.", "Minha diversidade étnica é celebrada em festas e rituais."
      ]
    },

    {
      "name": "Estados Unidos",
      "clues": [
        "Sou uma das maiores potências mundiais.", "Minha história é marcada por imigração e diversidade.", "Sou referência em tecnologia, cinema e música.", "Minha economia é uma das mais influentes do planeta.", "Sou composto por 50 estados.",
        "Minha bandeira tem estrelas e listras.", "Sou palco de grandes eventos esportivos.", "Minha cultura pop é exportada globalmente.", "Sou símbolo de liberdade e oportunidades.", "Minha influência política é global.",
        "Sou lar de parques nacionais famosos.", "Minha história envolve guerras e conquistas.", "Sou referência em inovação científica.", "Minha gastronomia é marcada por diversidade regional.", "Sou destino de turistas do mundo inteiro.",
        "Minha música influencia estilos globais.", "Sou símbolo de democracia e direitos civis.", "Minha arquitetura mistura tradição e modernidade.", "Sou inspiração para filmes e séries.", "Minha cultura é celebrada em festivais e feriados."
      ]
    },

    {
      "name": "África",
      "clues": [
        "Sou o segundo maior continente do mundo.", "Minha diversidade cultural e natural é imensa.", "Sou berço da humanidade.", "Minha fauna inclui leões, elefantes e girafas.", "Sou composto por mais de 50 países.",
        "Minha história é marcada por civilizações antigas.", "Sou palco de desafios sociais e ambientais.", "Minha música e arte influenciam o mundo.", "Sou símbolo de resistência e riqueza cultural.", "Minha paisagem vai de desertos a florestas tropicais.",
        "Sou lar de povos e línguas diversas.", "Minha culinária é rica e variada.", "Sou referência em arte tribal e máscaras.", "Minha história envolve colonização e independência.", "Sou destino de safáris e aventuras.",
        "Minha cultura é celebrada em festivais coloridos.", "Sou inspiração para escritores e cineastas.", "Minha paisagem inclui savanas e montanhas.", "Sou símbolo de esperança e renovação.", "Minha história é marcada por superação e transformação."
      ]
    },

    {
      "name": "Mercado Municipal de São Paulo",
      "clues": [
        "Sou famoso por meu sanduíche de mortadela.", "Minha arquitetura é histórica e imponente.", "Sou ponto turístico e gastronômico da cidade.", "Ofereço frutas exóticas e especiarias.", "Sou referência em culinária paulistana.",
        "Minha localização é central.", "Sou palco de eventos culturais.", "Minha história envolve comércio e tradição.", "Sou destino de chefs e gourmets.", "Minha fachada tem vitrais coloridos.",
        "Sou símbolo da cultura paulistana.", "Minha estrutura recebe milhares de visitantes.", "Sou inspiração para programas de TV e revistas.", "Minha história é marcada por diversidade de sabores.", "Sou referência em produtos típicos.",
        "Minha presença é marcante em roteiros turísticos.", "Sou cenário de encontros gastronômicos.", "Minha tradição é celebrada por moradores e turistas.", "Sou símbolo de comércio e hospitalidade.", "Minha história envolve transformações urbanas."
      ]
    },

    {
      "name": "Cristo Redentor",
      "clues": [
        "Sou uma das sete maravilhas do mundo moderno.", "Minha vista panorâmica é famosa internacionalmente.", "Estou localizado no topo do Corcovado.", "Sou símbolo do Rio de Janeiro.", "Minha imagem é reconhecida mundialmente.",
        "Sou destino de turistas e peregrinos.", "Minha inauguração foi em 1931.", "Sou tema de cartões-postais e filmes.", "Minha altura impressiona visitantes.", "Sou símbolo de fé e acolhimento.",
        "Sou inspiração para artistas e fotógrafos.", "Minha presença é marcante em celebrações religiosas.", "Sou referência em turismo internacional.", "Minha história envolve engenharia e dedicação.", "Sou símbolo de paz e esperança.",
        "Minha imagem é celebrada em eventos esportivos.", "Sou tema de reportagens e documentários.", "Minha localização oferece vistas únicas da cidade.", "Sou inspiração para músicas e poesias.", "Minha história é marcada por devoção e orgulho nacional."
      ]
    },

    {
      "name": "Veneza",
      "clues": [
        "Sou famosa por meus canais e gôndolas.", "Minha arquitetura é marcada por palácios e igrejas.", "Sou palco do Carnaval mais tradicional da Itália.", "Minha Praça de São Marcos é icônica.", "Sou destino de casais apaixonados.",
        "Minha história envolve comércio marítimo.", "Sou referência em arte e cultura renascentista.", "Minha cidade é construída sobre estacas de madeira.", "Sou inspiração para pintores e escritores.", "Minha beleza é única no mundo.",
        "Sou símbolo de romance e mistério.", "Minha gastronomia é marcada por frutos do mar.", "Sou tema de filmes e livros famosos.", "Minha história envolve reis e navegadores.", "Sou referência em máscaras e fantasias.",
        "Minha paisagem muda com as estações.", "Sou inspiração para fotógrafos e artistas.", "Minha cultura é celebrada em festivais anuais.", "Sou símbolo de resistência à modernidade.", "Minha história é marcada por enchentes e reconstruções."
      ]
    },

    {
      "name": "Deserto do Saara",
      "clues": [
        "Sou o maior deserto quente do mundo.", "Minha extensão cobre vários países africanos.", "Sou conhecido por minhas dunas e oásis.", "Minha fauna inclui camelos e répteis.", "Sou palco de expedições e aventuras.",
        "Minha temperatura pode ser extrema.", "Sou símbolo de resistência e sobrevivência.", "Minha paisagem é marcada por silêncio e vastidão.", "Sou inspiração para filmes e histórias.", "Minha história envolve povos nômades.",
        "Sou tema de estudos sobre clima e geografia.", "Minha areia é palco de corridas e desafios.", "Sou referência em caravanas históricas.", "Minha paisagem muda com o vento.", "Sou símbolo de mistério e fascínio.",
        "Minha história é marcada por descobertas arqueológicas.", "Sou inspiração para exploradores e cientistas.", "Minha cultura é celebrada em músicas e danças.", "Sou cenário de lendas e mitos.", "Minha presença é sentida em todo o continente africano."
      ]
    },

    {
      "name": "Austrália",
      "clues": [
        "Sou um país e continente ao mesmo tempo.", "Minha fauna inclui cangurus e coalas.", "Sou famosa pela Grande Barreira de Corais.", "Minha cidade mais populosa é Sydney.", "Sou referência em esportes radicais e natureza.",
        "Minha cultura é marcada por diversidade.", "Sou palco de eventos internacionais.", "Minha história envolve povos aborígenes.", "Sou símbolo de aventura e liberdade.", "Minha paisagem vai de desertos a florestas tropicais.",
        "Sou destino de turistas em busca de aventura.", "Minha gastronomia é marcada por influências asiáticas.", "Sou referência em preservação ambiental.", "Minha história envolve colonização britânica.", "Sou símbolo de inovação e criatividade.",
        "Minha cultura é celebrada em festivais e eventos.", "Sou inspiração para cineastas e escritores.", "Minha paisagem inclui praias e montanhas.", "Sou referência em esportes aquáticos.", "Minha história é marcada por superação e desenvolvimento."
      ]

    },

    {
      "name": "Museu do Louvre",
      "clues": [
        "Sou o museu mais visitado do mundo.", "Minha pirâmide de vidro é um ícone arquitetônico.", "Sou lar da Mona Lisa.", "Minha coleção inclui obras de diversas épocas.", "Sou referência em arte e cultura.",
        "Minha localização é central em Paris.", "Sou destino de turistas e estudiosos.", "Minha história envolve reis e revoluções.", "Sou inspiração para artistas.", "Minha estrutura é imponente e histórica.",
        "Sou símbolo de conhecimento e beleza.", "Minha arquitetura mistura estilos antigos e modernos.", "Sou referência em exposições temporárias.", "Minha história é marcada por transformações culturais.", "Sou inspiração para estudantes de arte.",
        "Minha presença é marcante em roteiros turísticos.", "Sou tema de documentários e reportagens.", "Minha coleção é admirada mundialmente.", "Sou símbolo de preservação histórica.", "Minha história envolve descobertas e restaurações."
      ]
    },

    {
      "name": "Ilha de Páscoa",
      "clues": [
        "Sou famosa por meus moais, estátuas gigantes de pedra.", "Minha localização é remota no Oceano Pacífico.", "Minha cultura é marcada por mistérios arqueológicos.", "Sou tema de estudos sobre civilizações antigas.", "Minha paisagem é de tirar o fôlego.","Sou símbolo de isolamento e resistência.", "Minha história envolve navegação e descobertas.", "Sou inspiração para exploradores.", "Minha fauna inclui aves e peixes exóticos.", "Minha beleza é única e intrigante.",
        "Sou referência em tradições polinésias.", "Minha história envolve rituais ancestrais.", "Sou tema de filmes e documentários.", "Minha cultura é celebrada em festivais locais.", "Sou símbolo de mistério e fascínio.",
        "Minha paisagem muda com as estações.", "Sou inspiração para arqueólogos e cientistas.", "Minha história é marcada por desafios ambientais.", "Sou referência em turismo de aventura.", "Minha presença é sentida em todo o mundo."
      ]
    },

    {
      "name": "Minas Gerais",
      "clues": [
        "Sou conhecido por minhas montanhas e cidades históricas.", "Minha culinária inclui pão de queijo e doce de leite.", "Sou berço do movimento da Inconfidência.", "Minha capital é Belo Horizonte.", "Sou referência em hospitalidade e tradição.",
        "Minha produção de café é destaque nacional.", "Sou lar de igrejas barrocas e arte colonial.", "Minha cultura é celebrada em festas como o Carnaval de Ouro Preto.", "Sou destino de turismo rural e ecológico.", "Minha história envolve mineração e desenvolvimento.",
        "Sou símbolo de riqueza mineral.", "Minha paisagem inclui vales e cachoeiras.", "Sou referência em literatura regional.", "Minha história é marcada por resistência e luta.", "Sou inspiração para músicos e poetas.",
        "Minha culinária é celebrada em festivais gastronômicos.", "Sou destino de turistas em busca de cultura e lazer.", "Minha tradição é preservada em museus e centros culturais.", "Sou símbolo de diversidade e criatividade.", "Minha história envolve progresso e inovação."
      ]
    },
    
    {
      "name": "Rio Grande do Sul",
      "clues": [
        "Sou conhecido por minha tradição gaúcha e chimarrão.", "Minha capital é Porto Alegre.", "Sou referência em vinhos e culinária típica.", "Minha cultura é marcada por festas como o Carnaval e a Semana Farroupilha.", "Sou lar de serras e cânions impressionantes.",
        "Minha história envolve imigração europeia.", "Sou destino de turismo rural e enoturismo.", "Minha economia é forte na agropecuária.", "Sou símbolo de orgulho regional.", "Minha paisagem inclui pampas e florestas.",
        "Sou referência em literatura regional.", "Minha música é marcada por ritmos tradicionais.", "Sou inspiração para artistas e escritores.", "Minha história é marcada por batalhas e conquistas.", "Sou símbolo de hospitalidade e tradição.",
        "Minha culinária inclui churrasco e pratos típicos.", "Sou destino de turistas em busca de cultura e lazer.", "Minha tradição é celebrada em festas populares.", "Sou referência em esportes equestres.", "Minha história envolve progresso e inovação."
      ]
    },

    {
      "name": "Pernambuco",
      "clues": [
        "Sou conhecido por meu frevo e maracatu.", "Minha capital é Recife.", "Sou lar de Olinda, patrimônio histórico da humanidade.", "Minha cultura é celebrada no Carnaval e nas festas juninas.", "Sou referência em praias como Porto de Galinhas.",
        "Minha história envolve resistência e revoluções.", "Sou destino de turismo cultural e ecológico.", "Minha culinária inclui bolo de rolo e carne de sol.", "Sou símbolo de diversidade e criatividade.", "Minha paisagem vai de litoral a sertão.",
        "Sou referência em literatura regional.", "Minha música influencia o Brasil inteiro.", "Sou inspiração para artistas e escritores.", "Minha história é marcada por superação e desenvolvimento.", "Sou símbolo de hospitalidade e tradição.",
        "Minha culinária é celebrada em festivais gastronômicos.", "Sou destino de turistas em busca de cultura e lazer.", "Minha tradição é preservada em museus e centros culturais.", "Sou referência em festas populares.", "Minha história envolve progresso e inovação."
      ]
    },

    {
      "name": "Amazonas",
      "clues": [
        "Sou o maior estado do Brasil em extensão territorial.", "Minha capital é Manaus.", "Sou referência em biodiversidade e floresta tropical.", "Minha cultura é marcada por festas como o Festival de Parintins.", "Sou lar de povos indígenas e comunidades ribeirinhas.",
        "Minha economia envolve extrativismo e turismo ecológico.", "Sou símbolo de preservação ambiental.", "Minha história envolve exploração e desenvolvimento sustentável.", "Sou destino de aventuras na selva.", "Minha paisagem é dominada pela floresta amazônica.",
        "Sou referência em literatura regional.", "Minha música é marcada por ritmos amazônicos.", "Sou inspiração para artistas e escritores.", "Minha história é marcada por superação e desenvolvimento.", "Sou símbolo de hospitalidade e tradição.",
        "Minha culinária inclui peixes típicos e frutas exóticas.", "Sou destino de turistas em busca de cultura e lazer.", "Minha tradição é preservada em festas populares.", "Sou referência em turismo ecológico.", "Minha história envolve progresso e inovação."
      ]
    },

    {
      "name": "Ceará",
      "clues": [
        "Sou conhecido por minhas praias paradisíacas e falésias.", "Minha capital é Fortaleza.", "Sou referência em humor e cultura popular.", "Minha culinária inclui carne de sol e tapioca.", "Sou lar de festas como o Fortal e o Carnaval de rua.",
        "Minha história envolve resistência e desenvolvimento.", "Sou destino de turismo ecológico e esportivo.", "Minha paisagem vai de litoral a sertão.", "Sou símbolo de criatividade e alegria.", "Minha cultura é celebrada em todo o Brasil.",
        "Sou referência em literatura regional.", "Minha música influencia o Brasil inteiro.", "Sou inspiração para artistas e escritores.", "Minha história é marcada por superação e desenvolvimento.", "Sou símbolo de hospitalidade e tradição.",
        "Minha culinária é celebrada em festivais gastronômicos.", "Sou destino de turistas em busca de cultura e lazer.", "Minha tradição é preservada em museus e centros culturais.", "Sou referência em festas populares.", "Minha história envolve progresso e inovação."
      ]
    },

    {
      "name": "Acre",
      "clues": [
        "Sou um estado brasileiro localizado na região Norte.", "Minha capital é Rio Branco.", "Sou conhecido por minha floresta amazônica e biodiversidade.", "Minha história envolve lutas pela anexação ao Brasil.", "Sou referência em seringais e produção de borracha.",
        "Minha cultura é marcada por festas populares e tradições indígenas.", "Sou destino de turismo ecológico e de aventura.", "Minha economia envolve extrativismo e agricultura.", "Sou símbolo de resistência e preservação ambiental.", "Minha paisagem é dominada por rios e florestas.",
        "Sou referência em literatura regional.", "Minha música é marcada por ritmos amazônicos.", "Sou inspiração para artistas e escritores.", "Minha história é marcada por superação e desenvolvimento.", "Sou símbolo de hospitalidade e tradição.",
        "Minha culinária inclui peixes típicos e frutas exóticas.", "Sou destino de turistas em busca de cultura e lazer.", "Minha tradição é preservada em festas populares.", "Sou referência em turismo ecológico.", "Minha história envolve progresso e inovação."
      ]
    },

    {
      "name": "McDonald's",
      "clues": [
        "Sou uma das maiores redes de fast-food do mundo.", "Meu símbolo é um M amarelo.", "Sou conhecido por hambúrgueres e batatas fritas.", "Minha presença é global, em mais de 100 países.", "Meu cardápio inclui o Big Mac e o McLanche Feliz.",
        "Sou referência em comida rápida e acessível.", "Minha história começou nos Estados Unidos.", "Sou tema de filmes e documentários sobre alimentação.", "Minha marca é reconhecida por crianças e adultos.", "Sou símbolo da cultura pop e do consumo moderno.",
        "Sou inspiração para campanhas publicitárias.", "Minha história envolve inovação no setor alimentício.", "Sou referência em franquias internacionais.", "Minha presença é marcante em grandes cidades.", "Sou símbolo de conveniência e rapidez.",
        "Minha marca é celebrada em datas especiais.", "Sou tema de estudos sobre alimentação global.", "Minha história é marcada por expansão e sucesso.", "Sou referência em marketing e comunicação.", "Minha presença é sentida em todo o mundo."
      ]
    },
 
    {
      "name": "Starbucks",
      "clues": [
        "Sou uma das maiores redes de cafeterias do mundo.", "Meu símbolo é uma sereia verde.", "Sou conhecido por cafés especiais e bebidas personalizadas.", "Minha presença é global, em grandes cidades.", "Meu ambiente é acolhedor e moderno.",
        "Sou referência em cultura de café.", "Minha história começou em Seattle, EUA.", "Sou destino de encontros e reuniões.", "Minha marca é reconhecida por jovens e adultos.", "Sou símbolo de estilo de vida urbano.",
        "Sou inspiração para campanhas publicitárias.", "Minha história envolve inovação no setor de cafeterias.", "Sou referência em franquias internacionais.", "Minha presença é marcante em grandes cidades.", "Sou símbolo de conveniência e modernidade.",
        "Minha marca é celebrada em datas especiais.", "Sou tema de estudos sobre cultura urbana.", "Minha história é marcada por expansão e sucesso.", "Sou referência em marketing e comunicação.", "Minha presença é sentida em todo o mundo."
      ]
    },
  
    {
      "name": "Outback Steakhouse",
      "clues": [
        "Sou uma rede de restaurantes inspirada na Austrália.", "Sou conhecido por costelas e carnes grelhadas.", "Meu prato mais famoso é a Bloomin' Onion.", "Meu ambiente é descontraído e temático.", "Minha presença é marcante em shoppings brasileiros.",
        "Sou referência em happy hour e porções generosas.", "Minha história começou nos Estados Unidos.", "Sou destino de famílias e grupos de amigos.", "Minha marca é reconhecida por qualidade e sabor.", "Sou símbolo de celebração e lazer.",
        "Sou inspiração para campanhas publicitárias.", "Minha história envolve inovação no setor de restaurantes.", "Sou referência em franquias internacionais.", "Minha presença é marcante em grandes cidades.", "Sou símbolo de conveniência e lazer.",
        "Minha marca é celebrada em datas especiais.", "Sou tema de estudos sobre gastronomia global.", "Minha história é marcada por expansão e sucesso.", "Sou referência em marketing e comunicação.", "Minha presença é sentida em todo o Brasil."
      ]
    },

    {
      "name": "Havaianas",
      "clues": [
        "Sou uma das marcas brasileiras mais conhecidas internacionalmente.", "Sou referência em sandálias de borracha.", "Minha origem é inspirada nas sandálias japonesas.", "Sou símbolo de verão e descontração.", "Minha presença é global, em lojas e praias.",
        "Minha história começou nos anos 1960.", "Sou tema de campanhas publicitárias criativas.", "Minha marca é associada à cultura brasileira.", "Sou usada por pessoas de todas as idades.", "Sou símbolo de praticidade e estilo casual.",
        "Sou inspiração para designers e estilistas.", "Minha história envolve inovação em moda.", "Sou referência em exportação de produtos brasileiros.", "Minha presença é marcante em grandes eventos.", "Sou símbolo de criatividade e simplicidade.",
        "Minha marca é celebrada em campanhas internacionais.", "Sou tema de estudos sobre cultura popular.", "Minha história é marcada por expansão global.", "Sou referência em marketing e comunicação.", "Minha presença é sentida em todo o mundo."
      ]
    },

    {
      "name": "Magazine Luiza",
      "clues": [
        "Sou uma das maiores redes varejistas do Brasil.", "Minha história começou em Franca, interior de São Paulo.", "Sou referência em inovação digital e comércio eletrônico.", "Minha marca é reconhecida nacionalmente.", "Sou destino de compras de eletrodomésticos e eletrônicos.",
        "Sou símbolo de empreendedorismo feminino.", "Minha presença é marcante em shoppings e lojas físicas.", "Sou tema de campanhas publicitárias criativas.", "Minha cultura valoriza o atendimento ao cliente.", "Sou símbolo de modernidade e crescimento econômico.",
        "Sou inspiração para outras empresas do setor.", "Minha história envolve superação e inovação.", "Sou referência em tecnologia e atendimento.", "Minha presença é marcante em datas comemorativas.", "Sou símbolo de confiança e tradição.",
        "Minha marca é celebrada em campanhas nacionais.", "Sou tema de estudos sobre varejo brasileiro.", "Minha história é marcada por expansão e sucesso.", "Sou referência em marketing e comunicação.", "Minha presença é sentida em todo o Brasil."
      ]
    },
    {
      "name": "Chapada Diamantina",
      "clues": [
        "Sou marcada por formações rochosas e cânions impressionantes.", "Minha biodiversidade é única no Brasil.", "Sou destino de trilhas desafiadoras e cachoeiras secretas.", "Minha história envolve mineração e exploração.", "Sou inspiração para aventureiros e fotógrafos.",
        "Minha paisagem é composta por vales e grutas misteriosas.", "Sou lar de comunidades tradicionais e quilombolas.", "Minha flora inclui espécies raras e endêmicas.", "Sou referência em ecoturismo e preservação ambiental.", "Minha fama atravessa gerações de exploradores.",
        "Sou tema de documentários e estudos científicos.", "Minha cultura é celebrada em festas regionais.", "Sou símbolo de resistência ambiental.", "Minha presença é marcante em roteiros de aventura.", "Sou inspiração para artistas e escritores.",
        "Minha história envolve lendas e mitos locais.", "Sou destino de quem busca paz e natureza.", "Minha imagem é reconhecida mundialmente.", "Sou símbolo de beleza natural.", "Meu nome é sinônimo de paisagem deslumbrante."
      ]
    },
    {
      "name": "Ilha de Fernando de Noronha",
      "clues": [
        "Sou formada por ilhas vulcânicas no Atlântico.", "Minha biodiversidade marinha é protegida por leis ambientais.", "Sou destino de mergulhadores e amantes da natureza.", "Minha história envolve descobertas e ocupações militares.", "Sou inspiração para fotógrafos e cineastas.",
        "Minha paisagem inclui praias paradisíacas e falésias.", "Sou lar de espécies endêmicas e ameaçadas.", "Minha fama é internacional entre turistas ecológicos.", "Sou referência em preservação ambiental.", "Minha beleza é celebrada em rankings mundiais.",
        "Sou tema de reportagens e documentários.", "Minha cultura é marcada por festas locais.", "Sou símbolo de sustentabilidade.", "Minha presença é marcante em roteiros de aventura.", "Sou inspiração para artistas e escritores.",
        "Minha história envolve lendas e mitos do mar.", "Sou destino de quem busca tranquilidade e exclusividade.", "Minha imagem é reconhecida mundialmente.", "Sou símbolo de paraíso natural.", "Meu nome é sinônimo de beleza intocada."
      ]
    },
    {
      "name": "Petra",
      "clues": [
        "Sou uma cidade esculpida em rochas avermelhadas.", "Minha história envolve povos nabateus e rotas comerciais.", "Sou Patrimônio Mundial da UNESCO.", "Minha arquitetura é marcada por túmulos e templos monumentais.", "Sou inspiração para arqueólogos e exploradores.",
        "Minha paisagem é desértica e misteriosa.", "Sou tema de filmes e documentários históricos.", "Minha fama atravessa séculos de descobertas.", "Sou referência em engenharia antiga.", "Minha beleza é celebrada por visitantes do mundo todo.",
        "Sou símbolo de resistência e sobrevivência.", "Minha cultura é marcada por lendas e mitos.", "Sou inspiração para artistas e escritores.", "Minha presença é marcante em roteiros de aventura.", "Sou destino de quem busca história e mistério.",
        "Minha imagem é reconhecida mundialmente.", "Sou símbolo de maravilha arqueológica.", "Minha história envolve conquistas e perdas.", "Sou referência em turismo histórico.", "Meu nome é sinônimo de cidade perdida."
      ]
    },
    {
      "name": "Serengeti",
      "clues": [
        "Sou uma vasta planície africana.", "Minha fauna inclui leões, zebras e gnus.", "Sou palco da maior migração de mamíferos do mundo.", "Minha história envolve povos nômades e conservação ambiental.", "Sou inspiração para documentários e estudos científicos.",
        "Minha paisagem é marcada por savanas e rios sazonais.", "Sou lar de tribos tradicionais.", "Minha fama é internacional entre amantes da natureza.", "Sou referência em safáris e turismo ecológico.", "Minha beleza é celebrada em fotografias premiadas.",
        "Sou tema de reportagens e filmes.", "Minha cultura é marcada por rituais ancestrais.", "Sou símbolo de biodiversidade.", "Minha presença é marcante em roteiros de aventura.", "Sou inspiração para artistas e escritores.",
        "Minha história envolve lendas e mitos africanos.", "Sou destino de quem busca contato com a vida selvagem.", "Minha imagem é reconhecida mundialmente.", "Sou símbolo de natureza exuberante.", "Meu nome é sinônimo de planície selvagem."
      ]
    },
    {
      "name": "Avenida Paulista",
      "clues": [
        "Sou um dos principais centros financeiros da América Latina.", "Minha arquitetura mistura estilos modernos e históricos.", "Sou palco de manifestações culturais e políticas.", "Minha história envolve expansão urbana e desenvolvimento.", "Sou inspiração para artistas e fotógrafos.",
        "Minha paisagem é marcada por arranha-céus e museus.", "Sou lar de centros culturais e galerias de arte.", "Minha fama é internacional entre turistas e moradores.", "Sou referência em lazer e entretenimento.", "Minha beleza é celebrada em eventos e festivais.",
        "Sou tema de reportagens e documentários.", "Minha cultura é marcada por diversidade e inovação.", "Sou símbolo de modernidade paulistana.", "Minha presença é marcante em roteiros turísticos.", "Sou inspiração para escritores e cineastas.",
        "Minha história envolve lendas urbanas.", "Sou destino de quem busca cultura e agitação.", "Minha imagem é reconhecida mundialmente.", "Sou símbolo de progresso.", "Meu nome é sinônimo de coração de São Paulo."
      ]
    },
    {
      "name": "Parque Ibirapuera",
      "clues": [
        "Sou um dos maiores parques urbanos do Brasil.", "Minha área abriga museus e espaços culturais.", "Sou referência em lazer e atividades ao ar livre.", "Minha história envolve urbanismo e paisagismo.", "Sou inspiração para fotógrafos e esportistas.",
        "Minha paisagem é composta por lagos e jardins.", "Sou lar de eventos culturais e festivais.", "Minha fama é nacional entre turistas e moradores.", "Sou símbolo de sustentabilidade e preservação ambiental.", "Minha beleza é celebrada em exposições e passeios.",
        "Sou tema de reportagens e documentários.", "Minha cultura é marcada por diversidade de atividades.", "Sou inspiração para artistas e arquitetos.", "Minha presença é marcante em roteiros turísticos.", "Sou referência em qualidade de vida.",
        "Minha história envolve projetos de Oscar Niemeyer.", "Sou destino de quem busca tranquilidade e lazer.", "Minha imagem é reconhecida mundialmente.", "Sou símbolo de natureza urbana.", "Meu nome é sinônimo de pulmão verde de São Paulo."
      ]
    },
    {
      "name": "Catedral da Sé",
      "clues": [
        "Sou um dos maiores templos neogóticos do mundo.", "Minha arquitetura é marcada por vitrais e torres imponentes.", "Sou referência em história religiosa e cultural.", "Minha história envolve fundação e desenvolvimento da cidade.", "Sou inspiração para artistas e fotógrafos.",
        "Minha paisagem é composta por praças e monumentos.", "Sou lar de celebrações religiosas e eventos culturais.", "Minha fama é nacional entre turistas e fiéis.", "Sou símbolo de fé e tradição paulistana.", "Minha beleza é celebrada em missas e cerimônias.",
        "Sou tema de reportagens e documentários.", "Minha cultura é marcada por diversidade religiosa.", "Sou inspiração para arquitetos e historiadores.", "Minha presença é marcante em roteiros turísticos.", "Sou referência em patrimônio histórico.",
        "Minha história envolve restaurações e preservação.", "Sou destino de quem busca espiritualidade e cultura.", "Minha imagem é reconhecida mundialmente.", "Sou símbolo de encontro e convivência.", "Meu nome é sinônimo de marco central de São Paulo."
      ]
    },
    {
      "name": "Mercadão de São Paulo",
      "clues": [
        "Sou famoso por meu sanduíche de mortadela e pastel de bacalhau.", "Minha arquitetura é histórica e imponente.", "Sou ponto turístico e gastronômico da cidade.", "Ofereço frutas exóticas e especiarias.", "Sou referência em culinária paulistana.",
        "Minha localização é central e estratégica.", "Sou palco de eventos culturais e feiras.", "Minha história envolve comércio e tradição.", "Sou destino de chefs e gourmets.", "Minha fachada tem vitrais coloridos e arcos monumentais.",
        "Sou símbolo da cultura paulistana.", "Minha estrutura recebe milhares de visitantes diariamente.", "Sou inspiração para programas de TV e revistas.", "Minha história é marcada por diversidade de sabores.", "Sou referência em produtos típicos e importados.",
        "Minha presença é marcante em roteiros turísticos.", "Sou cenário de encontros gastronômicos.", "Minha tradição é celebrada por moradores e turistas.", "Sou símbolo de comércio e hospitalidade.", "Meu nome é sinônimo de mercado municipal."
      ]
    },
    {
      "name": "Curitiba",
      "clues": [
        "Sou referência em planejamento urbano e sustentabilidade.", "Minha história envolve imigração europeia e inovação.", "Sou inspiração para arquitetos e urbanistas.", "Minha paisagem é marcada por parques e bosques.", "Sou lar de museus e espaços culturais.",
        "Minha fama é nacional por transporte público eficiente.", "Sou símbolo de qualidade de vida.", "Minha gastronomia é influenciada por diversas culturas.", "Sou palco de eventos culturais e festivais.", "Minha beleza é celebrada em roteiros turísticos.",
        "Sou tema de reportagens sobre cidades inteligentes.", "Minha cultura é marcada por diversidade e tradição.", "Sou inspiração para artistas e escritores.", "Minha presença é marcante em roteiros ecológicos.", "Sou referência em inovação ambiental.",
        "Minha história envolve crescimento acelerado.", "Sou destino de quem busca tranquilidade e lazer.", "Minha imagem é reconhecida mundialmente.", "Sou símbolo de cidade modelo.", "Meu nome é sinônimo de capital ecológica."
      ]
    },
    {
      "name": "Recife",
      "clues": [
        "Sou conhecida como a Veneza Brasileira.", "Minha história envolve colonização e resistência.", "Sou inspiração para músicos e poetas.", "Minha paisagem é marcada por rios e pontes.", "Sou lar de festas populares e manifestações culturais.",
        "Minha fama é nacional por praias e carnaval.", "Sou símbolo de diversidade cultural.", "Minha gastronomia inclui pratos típicos do Nordeste.", "Sou palco de eventos históricos e artísticos.", "Minha beleza é celebrada em roteiros turísticos.",
        "Sou tema de reportagens sobre cultura nordestina.", "Minha cultura é marcada por tradição e inovação.", "Sou inspiração para cineastas e escritores.", "Minha presença é marcante em roteiros históricos.", "Sou referência em literatura regional.",
        "Minha história envolve lutas e conquistas.", "Sou destino de quem busca cultura e lazer.", "Minha imagem é reconhecida mundialmente.", "Sou símbolo de cidade multicultural.", "Meu nome é sinônimo de capital do frevo."
      ]
    },
    {
      "name": "Fortaleza",
      "clues": [
        "Sou conhecida por minhas praias paradisíacas e falésias.", "Minha história envolve resistência e desenvolvimento.", "Sou inspiração para humoristas e artistas.", "Minha paisagem é marcada por dunas e lagoas.", "Sou lar de festas populares e eventos culturais.",
        "Minha fama é nacional por turismo e gastronomia.", "Sou símbolo de alegria e hospitalidade.", "Minha gastronomia inclui pratos típicos do Ceará.", "Sou palco de eventos esportivos e musicais.", "Minha beleza é celebrada em roteiros turísticos.",
        "Sou tema de reportagens sobre cultura nordestina.", "Minha cultura é marcada por tradição e inovação.", "Sou inspiração para escritores e cineastas.", "Minha presença é marcante em roteiros de lazer.", "Sou referência em literatura regional.",
        "Minha história envolve superação e crescimento.", "Sou destino de quem busca sol e diversão.", "Minha imagem é reconhecida mundialmente.", "Sou símbolo de cidade acolhedora.", "Meu nome é sinônimo de capital do sol."
      ]
    },
    {
      "name": "Porto Alegre",
      "clues": [
        "Sou conhecida por minha tradição gaúcha e chimarrão.", "Minha história envolve imigração europeia e desenvolvimento.", "Sou inspiração para músicos e escritores.", "Minha paisagem é marcada por parques e rios.", "Sou lar de festas populares e eventos culturais.",
        "Minha fama é nacional por hospitalidade e cultura.", "Sou símbolo de orgulho regional.", "Minha gastronomia inclui pratos típicos do Sul.", "Sou palco de eventos literários e artísticos.", "Minha beleza é celebrada em roteiros turísticos.",
        "Sou tema de reportagens sobre cultura gaúcha.", "Minha cultura é marcada por tradição e inovação.", "Sou inspiração para cineastas e artistas.", "Minha presença é marcante em roteiros históricos.", "Sou referência em literatura regional.",
        "Minha história envolve lutas e conquistas.", "Sou destino de quem busca cultura e lazer.", "Minha imagem é reconhecida mundialmente.", "Sou símbolo de cidade amiga.", "Meu nome é sinônimo de capital dos pampas."
      ]
    },
    {
      "name": "Pindamonhangaba",
      "clues": [
        "Sou conhecida por meu nome de origem tupi, que significa 'lugar onde se fazem anzóis'.", "Minha história envolve bandeirantes e tropeiros.", "Sou inspiração para estudiosos da cultura paulista.", "Minha paisagem é marcada pela Serra da Mantiqueira.", "Sou lar de festas tradicionais e manifestações culturais.",
        "Minha fama é regional por produção agrícola e industrial.", "Sou símbolo de desenvolvimento no Vale do Paraíba.", "Minha gastronomia inclui pratos típicos do interior paulista.", "Sou palco de eventos esportivos e culturais.", "Minha beleza é celebrada em roteiros turísticos do interior.",
        "Sou tema de reportagens sobre cidades históricas.", "Minha cultura é marcada por tradição e inovação.", "Sou inspiração para escritores e artistas locais.", "Minha presença é marcante em roteiros ecológicos.", "Sou referência em história paulista.",
        "Minha história envolve lutas e progresso.", "Sou destino de quem busca tranquilidade e lazer.", "Minha imagem é reconhecida regionalmente.", "Sou símbolo de cidade acolhedora.", "Meu nome é sinônimo de tradição do Vale do Paraíba."
      ]
    }
    ,
    {
      "name": "Rio Jordão",
      "clues": [
        "Sou um dos rios mais citados em textos religiosos antigos.",
        "Minha importância é central em narrativas bíblicas.",
        "Fui cenário de travessias históricas e milagres.",
        "Meu curso separa terras sagradas e regiões históricas.",
        "Sou símbolo de renovação espiritual e fé.",
        "Minhas águas foram palco de batismos famosos.",
        "Sou referência em peregrinações e rituais.",
        "Minha nascente está nas montanhas do Líbano.",
        "Deságuo no Mar Morto, um dos pontos mais baixos da Terra.",
        "Sou inspiração para músicas, poemas e orações.",
        "Minha história envolve povos antigos e conflitos.",
        "Sou tema de estudos arqueológicos e geográficos.",
        "Minha paisagem é marcada por vales e margens férteis.",
        "Sou símbolo de passagem e transformação.",
        "Minha fama ultrapassa fronteiras religiosas.",
        "Sou destino de turistas e fiéis do mundo inteiro.",
        "Minha imagem é celebrada em arte sacra.",
        "Sou referência em mapas históricos do Oriente Médio.",
        "Minha presença é marcante em relatos de profetas.",
        "Meu nome é sinônimo de rio sagrado."
      ]
    }
    ,
    {
      "name": "Jerusalém",
      "clues": [
        "Sou uma das cidades mais antigas do mundo ainda habitadas.",
        "Minha história é marcada por conquistas, destruições e reconstruções.",
        "Sou considerada sagrada por três grandes religiões.",
        "Meu Muro das Lamentações é símbolo de fé judaica.",
        "Sou lar da Igreja do Santo Sepulcro, importante para cristãos.",
        "Minha Esplanada das Mesquitas é reverenciada por muçulmanos.",
        "Sou palco de peregrinações e celebrações religiosas.",
        "Minha paisagem mistura muralhas antigas e construções modernas.",
        "Sou tema de estudos arqueológicos e históricos.",
        "Minha cultura é marcada por diversidade e tradição.",
        "Sou inspiração para escritores, artistas e cineastas.",
        "Minha história envolve reis, profetas e imperadores.",
        "Sou símbolo de esperança, paz e conflito.",
        "Minha fama ultrapassa fronteiras e gerações.",
        "Sou destino de turistas e fiéis do mundo inteiro.",
        "Minha imagem é celebrada em arte sacra e literatura.",
        "Sou referência em mapas antigos e modernos.",
        "Minha presença é marcante em relatos bíblicos e históricos.",
        "Sou cenário de eventos que mudaram o curso da humanidade.",
        "Meu nome é sinônimo de cidade sagrada e eterna."
      ]
    }
    ,
    {
      "name": "Israel",
      "clues": [
        "Sou um país do Oriente Médio com história milenar.",
        "Minha terra é considerada sagrada por várias religiões.",
        "Sou lar de cidades históricas como Jerusalém.",
        "Minha cultura é marcada por diversidade e inovação.",
        "Sou referência em tecnologia e ciência.",
        "Minha paisagem inclui desertos, vales e o Mar Morto.",
        "Sou palco de conflitos e acordos de paz.",
        "Minha gastronomia mistura sabores do Mediterrâneo e do Oriente.",
        "Sou destino de peregrinações religiosas e turismo histórico.",
        "Minha história envolve reis, profetas e impérios antigos.",
        "Sou símbolo de resiliência e reconstrução.",
        "Minha fama ultrapassa fronteiras políticas e culturais.",
        "Sou inspiração para escritores, cineastas e artistas.",
        "Minha ciência é reconhecida mundialmente.",
        "Sou referência em agricultura inovadora.",
        "Minha população é formada por diferentes etnias e crenças.",
        "Sou tema de estudos arqueológicos e bíblicos.",
        "Minha presença é marcante em debates internacionais.",
        "Sou cenário de eventos que mudaram o curso da história.",
        "Meu nome é sinônimo de terra prometida e inovação."
      ]
    }


  ]
}
